djreviews/__init__.py
djreviews/admin.py
djreviews/app.py
djreviews/models.py
djreviews/settings.py
djreviews/tests.py
djreviews/urls.py
djreviews/utils.py
djreviews/views.py
djreviews-0.0.1.dist-info/METADATA
djreviews-0.0.1.dist-info/WHEEL
djreviews-0.0.1.dist-info/top_level.txt
djreviews-0.0.1.dist-info/RECORD
