Metadata-Version: 2.1
Name: djreviews
Version: 0.0.1
Summary: Adding Reviews to your django app.
Author-email: Jack Kweyunga <jackkweyunga@atomatiki.tech>
License: MIT
Keywords: django reviews
Classifier: Framework :: Django
Classifier: Programming Language :: Python :: 3
Requires-Python: >=3.8
Requires-Dist: importlib-metadata ; python_version < "3.8"
